{
  "name": "website-carbon",
  "origin": "voxgig-sdk",
  "def": "website-carbon_0.1.0.json",
  "main": {
    "kit": {
      "info": {
        "contact": {
          "name": "Wholegrain Digital",
          "url": "https://www.websitecarbon.com/"
        },
        "description": "Calculates website carbon emissions per page view using real-time tests. Provides endpoints for testing and manual calculations to increase awareness and understanding of sustainability on the web.",
        "servers": [
          {
            "description": "Production server",
            "url": "https://api.websitecarbon.com"
          }
        ],
        "termsOfService": "https://www.websitecarbon.com/",
        "title": "Website Carbon API",
        "version": "1.0.0",
        "x-documentation": "https://api.websitecarbon.com/"
      },
      "config": {
        "auth": {
          "prefix": "Bearer"
        },
        "headers": {
          "content-type": "application/json"
        }
      },
      "entity": {
        "data": {
          "alias": {
            "field": {}
          },
          "fields": [
            {
              "name": "byte",
              "req": true,
              "type": "`$NUMBER`",
              "active": true
            },
            {
              "name": "cleaner_than",
              "req": true,
              "type": "`$NUMBER`",
              "active": true
            },
            {
              "name": "gco2e",
              "req": true,
              "type": "`$NUMBER`",
              "active": true
            },
            {
              "name": "green",
              "req": true,
              "type": "`$BOOLEAN`",
              "active": true
            },
            {
              "name": "rating",
              "req": true,
              "type": "`$STRING`",
              "active": true
            },
            {
              "name": "statistic",
              "req": true,
              "type": "`$OBJECT`",
              "active": true
            }
          ],
          "name": "data",
          "op": {
            "load": {
              "name": "load",
              "points": [
                {
                  "args": {
                    "query": [
                      {
                        "example": 12345678,
                        "kind": "query",
                        "name": "byte",
                        "orig": "byte",
                        "reqd": true,
                        "type": "`$INTEGER`",
                        "active": true
                      },
                      {
                        "example": 1,
                        "kind": "query",
                        "name": "green",
                        "orig": "green",
                        "reqd": true,
                        "type": "`$INTEGER`",
                        "active": true
                      },
                      {
                        "kind": "query",
                        "name": "legacy",
                        "orig": "legacy",
                        "reqd": false,
                        "type": "`$INTEGER`",
                        "active": true
                      }
                    ]
                  },
                  "method": "GET",
                  "orig": "/data",
                  "parts": [
                    "data"
                  ],
                  "select": {
                    "exist": [
                      "byte",
                      "green",
                      "legacy"
                    ]
                  },
                  "transform": {
                    "req": "`reqdata`",
                    "res": "`body`"
                  },
                  "active": true
                }
              ],
              "input": "data"
            }
          },
          "active": true,
          "relations": {
            "ancestors": []
          }
        }
      },
      "feature": {
        "test": {
          "name": "test",
          "title": "In-memory mock transport for testing without a live server",
          "version": "0.0.1",
          "active": true,
          "config": {
            "options": {
              "active": false
            }
          },
          "hook": {
            "PostConstruct": {
              "active": true,
              "await": false
            },
            "PostConstructEntity": {
              "active": true,
              "await": false
            },
            "SetData": {
              "active": true,
              "await": false
            },
            "GetData": {
              "active": true,
              "await": false
            },
            "SetMatch": {
              "active": true
            },
            "GetMatch": {
              "active": true,
              "await": false
            },
            "PrePoint": {
              "active": true
            },
            "PreSpec": {
              "active": true,
              "await": false
            },
            "PreRequest": {
              "active": true,
              "await": false
            },
            "PreResponse": {
              "active": true,
              "await": false
            },
            "PreResult": {
              "active": true,
              "await": false
            },
            "PreTarget": {
              "active": false,
              "await": false
            },
            "PostOperation": {
              "active": false,
              "await": false
            }
          },
          "target": {
            "ts": {
              "deps": {}
            },
            "go": {
              "deps": {}
            },
            "lua": {
              "deps": {}
            },
            "php": {
              "deps": {}
            },
            "py": {
              "deps": {}
            },
            "rb": {
              "deps": {}
            },
            "go-cli": {
              "deps": {}
            }
          }
        }
      },
      "flow": {
        "BasicDataFlow": {
          "entity": "data",
          "kind": "basic",
          "name": "BasicDataFlow",
          "step": [
            {
              "input": {
                "ref": "data_ref01",
                "srcdatavar": "data_ref01_data",
                "suffix": "_dt0"
              },
              "op": "load",
              "valid": [
                {
                  "apply": "TextFieldMark",
                  "def": {
                    "mark": "Mark01-data_ref01"
                  }
                }
              ],
              "active": true,
              "match": {},
              "data": {},
              "spec": []
            }
          ],
          "key$": "BasicDataFlow",
          "active": true,
          "param": {}
        }
      },
      "target": {
        "go-cli": {
          "title": "Go CLI",
          "ext": "go",
          "comment": {
            "line": "//"
          },
          "module": {
            "name": "website-carbon"
          },
          "phase": {
            "entity": {
              "active": false
            },
            "feature": {
              "active": false
            },
            "readme": {
              "active": false
            },
            "test": {
              "active": false
            }
          },
          "deps": {},
          "name": "go-cli",
          "active": true
        },
        "ts": {
          "title": "TypeScript",
          "ext": "ts",
          "comment": {
            "line": "//"
          },
          "module": {
            "name": "website-carbon"
          },
          "base": "node_modules/@voxgig/sdkgen/project/.sdk",
          "deps": {
            "dotenv": {
              "active": true,
              "version": "^17.4.2",
              "kind": "dev"
            },
            "typescript": {
              "active": true,
              "version": "^5.9.3",
              "kind": "dev"
            },
            "@types/node": {
              "active": true,
              "version": "^25.6.0",
              "kind": "dev"
            }
          },
          "name": "ts",
          "active": true
        },
        "go": {
          "title": "Golang",
          "ext": "go",
          "comment": {
            "line": "//"
          },
          "module": {
            "name": "website-carbon"
          },
          "srcfeature": false,
          "deps": {},
          "name": "go",
          "active": true
        },
        "lua": {
          "title": "Lua",
          "ext": "lua",
          "comment": {
            "line": "--"
          },
          "module": {
            "name": "website-carbon"
          },
          "srcfeature": false,
          "deps": {
            "dkjson": {
              "active": true,
              "version": "2.5",
              "kind": "prod"
            }
          },
          "name": "lua",
          "active": true
        },
        "php": {
          "title": "PHP",
          "ext": "php",
          "comment": {
            "line": "//"
          },
          "module": {
            "name": "website-carbon"
          },
          "srcfeature": false,
          "deps": {},
          "name": "php",
          "active": true
        },
        "py": {
          "title": "Python",
          "ext": "py",
          "comment": {
            "line": "#"
          },
          "module": {
            "name": "website-carbon"
          },
          "srcfeature": false,
          "deps": {
            "requests": {
              "active": true,
              "version": "2.33",
              "kind": "prod"
            }
          },
          "name": "py",
          "active": true
        },
        "rb": {
          "title": "Ruby",
          "ext": "rb",
          "comment": {
            "line": "#"
          },
          "module": {
            "name": "website-carbon"
          },
          "srcfeature": false,
          "deps": {
            "voxgig-struct": {
              "active": true,
              "version": "0.0.10",
              "kind": "prod"
            },
            "json": {
              "active": true,
              "version": "0",
              "kind": "prod"
            }
          },
          "name": "rb",
          "active": true
        }
      },
      "option": {}
    },
    "def": {
      "desc": ""
    }
  }
}